Metadata-Version: 2.4
Name: hangman_helper_eldar
Version: 0.1.8
Summary: Helper library for Hangman game
Home-page: https://github.com/eldar/neszen_helper
Author: Eldar Eliyev
Author-email: liyev7773@gmail.com
Keywords: hangman game helper library
Classifier: Programming Language :: Python :: 3
Classifier: License :: OSI Approved :: MIT License
Classifier: Operating System :: OS Independent
Classifier: Topic :: Games/Entertainment :: Puzzle Games
Requires-Python: >=3.12
Dynamic: author
Dynamic: author-email
Dynamic: classifier
Dynamic: description-content-type
Dynamic: home-page
Dynamic: keywords
Dynamic: requires-python
Dynamic: summary
